{
  "$schema": "https://raw.githubusercontent.com/grafana/grafana/master/docs/sources/developers/plugins/plugin.schema.json",
  "type": "datasource",
  "name": "Grafana Fire Data Source Plugin",
  "id": "grafana-fire-datasource",
  "metrics": true,
  "backend": true,
  "executable": "gpx_fire-datasource",
  "info": {
    "description": "",
    "author": {
      "name": "Cyril Tovena",
      "url": "https://www.grafana.com"
    },
    "keywords": ["grafana", "datasource", "fire","flamegraph"],
    "logos": {
      "small": "img/logo.svg",
      "large": "img/logo.svg"
    },
    "links": [
      {
        "name": "Website",
        "url": "https://github.com/grafana/grafana-starter-datasource-backend"
      },
      {
        "name": "License",
        "url": "https://github.com/grafana/grafana-starter-datasource-backend/blob/master/LICENSE"
      }
    ],
    "screenshots": [],
    "version": "%VERSION%",
    "updated": "%TODAY%"
  },
  "dependencies": {
    "grafanaDependency": ">=7.0.0",
    "plugins": []
  }
}
